MANIFEST.in
README.md
setup.py
graph_peak_caller/__init__.py
graph_peak_caller/callpeaks.py
graph_peak_caller/callpeaks_interface.py
graph_peak_caller/command_line_interface.py
graph_peak_caller/custom_exceptions.py
graph_peak_caller/cut_narrowpeak_around_summit.py
graph_peak_caller/eventsorter.py
graph_peak_caller/haplotyping.py
graph_peak_caller/intervals.py
graph_peak_caller/linear_filter.py
graph_peak_caller/logging_config.py
graph_peak_caller/mindense.py
graph_peak_caller/multiplegraphscallpeaks.py
graph_peak_caller/peakcollection.py
graph_peak_caller/peakfasta.py
graph_peak_caller/preprocess_interface.py
graph_peak_caller/reporter.py
graph_peak_caller/sparsediffs.py
graph_peak_caller/sparsepvalues.py
graph_peak_caller/summits.py
graph_peak_caller/util.py
graph_peak_caller.egg-info/PKG-INFO
graph_peak_caller.egg-info/SOURCES.txt
graph_peak_caller.egg-info/dependency_links.txt
graph_peak_caller.egg-info/entry_points.txt
graph_peak_caller.egg-info/not-zip-safe
graph_peak_caller.egg-info/requires.txt
graph_peak_caller.egg-info/top_level.txt
graph_peak_caller/analysis/__init__.py
graph_peak_caller/analysis/__init__.pyc
graph_peak_caller/analysis/analyse_peaks.py
graph_peak_caller/analysis/analysis_interface.py
graph_peak_caller/analysis/datatables.py
graph_peak_caller/analysis/differentialbinding.py
graph_peak_caller/analysis/diploratio_v_motifrate.py
graph_peak_caller/analysis/fimowrapper.py
graph_peak_caller/analysis/genotype_matrix.py
graph_peak_caller/analysis/haplotype_finder.py
graph_peak_caller/analysis/macs_to_graph.py
graph_peak_caller/analysis/manually_classified_peaks.py
graph_peak_caller/analysis/motif_models.py
graph_peak_caller/analysis/motif_script.py
graph_peak_caller/analysis/motifenrichment.py
graph_peak_caller/analysis/motiflocations.py
graph_peak_caller/analysis/nongraphpeaks.py
graph_peak_caller/analysis/nongraphpeaks.pyc
graph_peak_caller/analysis/peakscomparer.py
graph_peak_caller/analysis/util.py
graph_peak_caller/analysis/venn_diagrams.py
graph_peak_caller/control/__init__.py
graph_peak_caller/control/__init__.pyc
graph_peak_caller/control/controlgenerator.py
graph_peak_caller/control/controlgenerator.pyc
graph_peak_caller/control/linearintervals.py
graph_peak_caller/control/linearintervals.pyc
