Metadata-Version: 1.1
Name: graph-peak-caller
Version: 1.2.2
Summary: Graph peak caller
Home-page: http://github.com/uio-bmi/graph_peak_caller
Author: Ivar Grytten and Knut Rand
Author-email: UNKNOWN
License: MIT
Platform: UNKNOWN
Classifier: Programming Language :: Python :: 3
